pyitt/__init__.py
pyitt/_funcutils.py
pyitt/_named_region.py
pyitt/_region.py
pyitt/collection_control.py
pyitt/counter.py
pyitt/domain.py
pyitt/event.py
pyitt/frame.py
pyitt/id.py
pyitt/native.cpython-311-x86_64-linux-musl.so
pyitt/pt_region.py
pyitt/string_handle.py
pyitt/task.py
pyitt/thread_naming.py
pyitt/compatibility_layers/__init__.py
pyitt/compatibility_layers/itt_python/__init__.py
pyitt/compatibility_layers/itt_python/domain.py
pyitt/compatibility_layers/itt_python/pt_region.py
pyitt/compatibility_layers/itt_python/task.py
pyitt/compatibility_layers/ittapi/__init__.py
pyitt/compatibility_layers/ittapi/event.py
pyitt/compatibility_layers/ittapi/pt_region.py
pyitt/compatibility_layers/ittapi/task.py
pyitt.libs/libgcc_s-0cd532bd.so.1
pyitt.libs/libstdc++-5d72f927.so.6.0.33
pyitt-1.7.5.dist-info/METADATA
pyitt-1.7.5.dist-info/WHEEL
pyitt-1.7.5.dist-info/top_level.txt
pyitt-1.7.5.dist-info/RECORD
pyitt-1.7.5.dist-info/licenses/LICENSE
pyitt-1.7.5.dist-info/licenses/ittapi/LICENSES/BSD-3-Clause.txt
