Metadata-Version: 2.4
Name: pyitt
Version: 1.7.5
Summary: Python bindings to Intel Instrumentation and Tracing Technology (ITT) API.
Author-email: Egor Suldin <rd3tap@yandex.ru>
Project-URL: Homepage, https://github.com/esuldin/pyitt
Project-URL: Bug Tracker, https://github.com/esuldin/pyitt/issues
Keywords: ittapi
Classifier: License :: OSI Approved :: BSD License
Classifier: Operating System :: Microsoft :: Windows
Classifier: Operating System :: POSIX :: Linux
Classifier: Programming Language :: Python :: 3.8
Classifier: Programming Language :: Python :: 3.9
Classifier: Programming Language :: Python :: 3.10
Classifier: Programming Language :: Python :: 3.11
Classifier: Programming Language :: Python :: 3.12
Classifier: Programming Language :: Python :: 3.13
Classifier: Programming Language :: Python :: 3.14
Requires-Python: >=3.8
License-File: LICENSE
License-File: ittapi/LICENSES/BSD-3-Clause.txt
Dynamic: license-file
